termcap/__init__.py
termcap/anim.py
termcap/asciicast.py
termcap/cli.py
termcap/cli_config.py
termcap/config.py
termcap/config_dirs.py
termcap/config_manager.py
termcap/term.py
termcap-0.1.1.dist-info/licenses/LICENSE
termcap-0.1.1.dist-info/licenses/LICENSE-BSD
termcap-0.1.1.dist-info/METADATA
termcap-0.1.1.dist-info/WHEEL
termcap-0.1.1.dist-info/entry_points.txt
termcap-0.1.1.dist-info/top_level.txt
termcap-0.1.1.dist-info/RECORD
